odl/__init__.py
odl/main.py
odl/models/__init__.py
odl/models/video_downloader.py
odl/providers/__init__.py
odl/providers/video.py
odl/providers/video_providers/__init__.py
odl/providers/video_providers/douyin.py
odl/providers/video_providers/tiktok.py
odl/providers/video_providers/video_provider.py
odl/providers/video_providers/youtube.py
odl/utils/__init__.py
odl/utils/helper.py
octopus_downloader-0.1.14.dist-info/METADATA
octopus_downloader-0.1.14.dist-info/WHEEL
octopus_downloader-0.1.14.dist-info/entry_points.txt
octopus_downloader-0.1.14.dist-info/RECORD
