Metadata-Version: 2.4
Name: octopus_downloader
Version: 0.1.14
Summary: Octopus Downloader CLI
Requires-Python: >=3.11
Requires-Dist: aiofiles==24.1.0
Requires-Dist: anyio==4.4.0
Requires-Dist: build>=1.2.2.post1
Requires-Dist: certifi==2024.8.30
Requires-Dist: click<8.2.0
Requires-Dist: h11==0.14.0
Requires-Dist: httpcore==1.0.5
Requires-Dist: httpx[socks]==0.27.2
Requires-Dist: idna==3.10
Requires-Dist: markdown-it-py==3.0.0
Requires-Dist: mdurl==0.1.2
Requires-Dist: pydantic>=2.11.4
Requires-Dist: pygments==2.18.0
Requires-Dist: python-dotenv==1.0.1
Requires-Dist: pywebio~=1.8.3
Requires-Dist: rich==13.7.1
Requires-Dist: sniffio==1.3.1
Requires-Dist: tikhub==1.12.7
Requires-Dist: twine>=6.1.0
Requires-Dist: typer>=0.15.3
Requires-Dist: websockets==12.0
